smsf/__init__.py
smsf-0.0.2.dist-info/licenses/LICENSE
smsf-0.0.2.dist-info/METADATA
smsf-0.0.2.dist-info/WHEEL
smsf-0.0.2.dist-info/top_level.txt
smsf-0.0.2.dist-info/RECORD
