Metadata-Version: 2.4
Name: smsf
Version: 0.0.2
Summary: Situation Model Space Framework
Author-email: Adrian Brasoveanu <abrsvn@gmail.com>
License-Expression: Apache-2.0
Project-URL: Homepage, https://github.com/abrsvn/smsf
Classifier: Development Status :: 3 - Alpha
Classifier: Intended Audience :: Developers
Classifier: Programming Language :: Python :: 3
Classifier: Programming Language :: Python :: 3.8
Classifier: Programming Language :: Python :: 3.9
Classifier: Programming Language :: Python :: 3.10
Classifier: Programming Language :: Python :: 3.11
Requires-Python: >=3.8
License-File: LICENSE
Dynamic: license-file
